xrpl_plugin/__init__.py
xrpl_plugin/basic_types.py
xrpl_plugin/keylets.py
xrpl_plugin/ledger_objects.py
xrpl_plugin/models.py
xrpl_plugin/nfts.py
xrpl_plugin/return_codes.py
xrpl_plugin/rippled_py.cpython-311-darwin.so
xrpl_plugin/sfields.py
xrpl_plugin/transactors.py
xrpl_plugin/build_scripts/CMakeLists.txt
xrpl_plugin/build_scripts/__init__.py
xrpl_plugin/build_scripts/build_cli.py
xrpl_plugin/build_scripts/conanfile.py
xrpl_plugin/rippled/.DS_Store
xrpl_plugin/rippled/.clang-format
xrpl_plugin/rippled/.codecov.yml
xrpl_plugin/rippled/.git
xrpl_plugin/rippled/.git-blame-ignore-revs
xrpl_plugin/rippled/.gitattributes
xrpl_plugin/rippled/.gitignore
xrpl_plugin/rippled/.pre-commit-config.yaml
xrpl_plugin/rippled/API-CHANGELOG.md
xrpl_plugin/rippled/BUILD.md
xrpl_plugin/rippled/CMakeLists.txt
xrpl_plugin/rippled/CONTRIBUTING.md
xrpl_plugin/rippled/LICENSE.md
xrpl_plugin/rippled/README.md
xrpl_plugin/rippled/RELEASENOTES.md
xrpl_plugin/rippled/SECURITY.md
xrpl_plugin/rippled/conanfile.py
xrpl_plugin/rippled/.github/.DS_Store
xrpl_plugin/rippled/.github/pull_request_template.md
xrpl_plugin/rippled/.github/ISSUE_TEMPLATE/bug_report.md
xrpl_plugin/rippled/.github/ISSUE_TEMPLATE/config.yml
xrpl_plugin/rippled/.github/ISSUE_TEMPLATE/feature_request.md
xrpl_plugin/rippled/.github/actions/build/action.yml
xrpl_plugin/rippled/.github/actions/dependencies/action.yml
xrpl_plugin/rippled/.github/workflows/clang-format.yml
xrpl_plugin/rippled/.github/workflows/doxygen.yml
xrpl_plugin/rippled/.github/workflows/levelization.yml
xrpl_plugin/rippled/.github/workflows/macos.yml
xrpl_plugin/rippled/.github/workflows/nix.yml
xrpl_plugin/rippled/.github/workflows/windows.yml
xrpl_plugin/rippled/Builds/.DS_Store
xrpl_plugin/rippled/Builds/README.md
xrpl_plugin/rippled/Builds/Test.py
xrpl_plugin/rippled/Builds/build_all.sh
xrpl_plugin/rippled/Builds/CMake/CMakeFuncs.cmake
xrpl_plugin/rippled/Builds/CMake/CMake_sqlite3.txt
xrpl_plugin/rippled/Builds/CMake/CodeCoverage.cmake
xrpl_plugin-0.2.1.dist-info/METADATA
xrpl_plugin-0.2.1.dist-info/WHEEL
xrpl_plugin-0.2.1.dist-info/entry_points.txt
xrpl_plugin-0.2.1.dist-info/top_level.txt
xrpl_plugin-0.2.1.dist-info/RECORD
