Metadata-Version: 2.1
Name: xrpl-plugin
Version: 0.2.1
Summary: XRPL Plugins
Home-page: https://github.com/mvadari/xrpl-plugin
Author: Mayukha Vadari
Author-email: mvadari@ripple.com
Requires-Python: >=3.8
